{
  "country_name": "Events",
  "country": "EV",
  "info": [
    {
      "id": "3344",
      "name": "Dutch: Eredivisie [CH3]",
      "tagline": "12 Apr 01:00 WIB - Groningen vs Go Ahead Eagles",
      "hls": "http://140.150.22.205/live/channel22.flv?wsSecret=7aa7c5403ea48300795871457a4bf1c3&wsABSTime=1775335358",
      "namespace": "Dutch: Eredivisie [CH3]",
      "is_live": "t",
      "is_movie": "f",
      "subtitle": "",
      "image": "https://api.orcatv.my.id/orca-stream/data-v1/source-images/4e72e5b38f5c7323bef92586b10426473ab7286640a5c5c6401469cd9d1a9308.png",
      "jenis": "ts",
      "premium": "f",
      "alpha_2_code": "EV",
      "country_name": "Events",
      "t_stamp": "1775930408",
      "s_stamp": "1775937900",
      "url_license": "https://etslive-v3-vidio-com-preview-tokenized.akamaized.net/live/17852/master.m3u8?hdnts=exp=1726126994~acl=/live/17852/master.m3u8!/hls-p/ingest_17852*/*!/hls-b/ingest_17852*/*~id=851110~hmac=7d99eba92a995ff011bebd28413b2ce3115295b25a6ae91d4de3686d5bc3b954",
      "fake_event": "f",
      "header_iptv": "{\"Host\":\"live1.pro2cdnlive.com\",\"Referer\":\"https://xl365.plcdn.xyz/\",\"Origin\":\"https://xl365.plcdn.xyz\",\"User-Agent\":\"Mozilla/5.0 (Windows NT 10.0; Win64; x64; rv:134.0) Gecko/20100101 Firefox/134.0\"}",
      "header_license": "{\"x-data\":\"none\"}",
      "category": "Events"
    },
    {
      "id": "973",
      "name": "Saudi Pro League [CH1]",
      "tagline": "12 Apr 01:00 WIB - Al Okhdood vs Al Nassr FC",
      "hls": "http://140.150.22.205/live/channel21.flv?wsSecret=8809fea0b09e25ba2de9ababd455da83&wsABSTime=1775336021",
      "namespace": "Saudi Pro League [CH1]",
      "is_live": "t",
      "is_movie": "f",
      "subtitle": "",
      "image": "https://api.orcatv.my.id/orca-stream/data-v1/source-images/d8d0c2bb77a3028b08f844582e2c8ebb27d634d291cfbe3ddb541d26ad3fae2e.png",
      "jenis": "ts",
      "premium": "f",
      "alpha_2_code": "EV",
      "country_name": "Events",
      "t_stamp": "1775930408",
      "s_stamp": "1775937900",
      "url_license": "https://etslive-v3-vidio-com-preview-tokenized.akamaized.net/live/17852/master.m3u8?hdnts=exp=1726126994~acl=/live/17852/master.m3u8!/hls-p/ingest_17852*/*!/hls-b/ingest_17852*/*~id=851110~hmac=7d99eba92a995ff011bebd28413b2ce3115295b25a6ae91d4de3686d5bc3b954",
      "fake_event": "f",
      "header_iptv": "{\"Host\":\"live1.pro2cdnlive.com\",\"Referer\":\"https://xl365.plcdn.xyz/\",\"Origin\":\"https://xl365.plcdn.xyz\",\"User-Agent\":\"Mozilla/5.0 (Windows NT 10.0; Win64; x64; rv:134.0) Gecko/20100101 Firefox/134.0\"}",
      "header_license": "{\"x-data\":\"none\"}",
      "category": "Events"
    },
    {
      "id": "3136",
      "name": "Major League Soccer [CH2]",
      "tagline": "12 Apr 01:30 WIB - Austin vs LA Galaxy",
      "hls": "https://a151aivottlinear-a.akamaihd.net/OTTB/pdx-nitro/live/clients/dash/enc/hm5nmxzgr4/out/v1/21aca259874c427c9ef9dc808b46f50f/cenc.mpd",
      "namespace": "Major League Soccer [CH2]",
      "is_live": "t",
      "is_movie": "f",
      "subtitle": "http://138.113.112.20/live/channel9.flv?wsSecret=2b403c0bfa34b36199c88f2e47b8ae95&wsABSTime=1750937822",
      "image": "https://api.orcatv.my.id/orca-stream/data-v1/source-images/f605938be462a80b66385bf2c49ec76c569e9108ec55155f535e311844f109c3.png",
      "jenis": "dash-clearkey",
      "premium": "f",
      "alpha_2_code": "EV",
      "country_name": "Events",
      "t_stamp": "1775932200",
      "s_stamp": "1775939400",
      "url_license": "eyJrZXlzIjpbeyJrdHkiOiJvY3QiLCJrIjoibHlpQUNqbFpxdjNWc0x6NzgzYUlFUSIsImtpZCI6IjBhRmprVTI0LzYwc1BwVDVlWWxxRFEifV0sInR5cGUiOiJ0ZW1wb3JhcnkifQ==",
      "fake_event": "f",
      "header_iptv": "{\"Referer\":\"none\",\"Origin\":\"none\",\"User-Agent\":\"Mozilla/5.0 (Windows NT 10.0; Win64; x64; rv:122.0) Gecko/20100101 Firefox/122.0\"}",
      "header_license": "{\"x-data\":\"none\"}",
      "category": "Events"
    },
    {
      "id": "3333",
      "name": "Italy: Serie-A [CH4]",
      "tagline": "12 Apr 01:45 WIB - Atalanta vs Juventus",
      "hls": "https://a201aivottlinear-a.akamaihd.net/OTTB/syd-nitro/live/clients/dash/enc/q4u5nwaogz/out/v1/18de6d3e65934f3a8de4358e69eab86c/cenc.mpd",
      "namespace": "Italy: Serie-A [CH4]",
      "is_live": "t",
      "is_movie": "f",
      "subtitle": "",
      "image": "https://api.orcatv.my.id/orca-stream/data-v1/source-images/1f616118d2517f8b6796d6636ee104f2373c2f9451bc195aa859742261e77e6e.png",
      "jenis": "dash-clearkey",
      "premium": "f",
      "alpha_2_code": "EV",
      "country_name": "Events",
      "t_stamp": "1775933108",
      "s_stamp": "1775940600",
      "url_license": "eyJrZXlzIjpbeyJrdHkiOiJvY3QiLCJrIjoiWjcydkhpRjF1ZjlvTDgzdzRqVkxIZyIsImtpZCI6ImVaWEhKS0UzU08yWENFQ29xMXU1c3cifV0sInR5cGUiOiJ0ZW1wb3JhcnkifQ==",
      "fake_event": "f",
      "header_iptv": "{\"Referer\":\"none\",\"Origin\":\"none\",\"User-Agent\":\"Mozilla/5.0 (Windows NT 10.0; Win64; x64; rv:123.0) Gecko/20100101 Firefox/123.0\"}",
      "header_license": "{\"x-data\":\"none\"}",
      "category": "Events"
    },
    {
      "id": "3349",
      "name": "Dutch: Eredivisie [CH4]",
      "tagline": "12 Apr 02:00 WIB - Heracles Almelo vs AFC Ajax",
      "hls": "http://140.150.22.205/live/channel16.flv?wsSecret=c923284276b9499a95da6e392c272da2&wsABSTime=1775410556",
      "namespace": "Dutch: Eredivisie [CH4]",
      "is_live": "t",
      "is_movie": "f",
      "subtitle": "",
      "image": "https://api.orcatv.my.id/orca-stream/data-v1/source-images/4e72e5b38f5c7323bef92586b10426473ab7286640a5c5c6401469cd9d1a9308.png",
      "jenis": "ts",
      "premium": "f",
      "alpha_2_code": "EV",
      "country_name": "Events",
      "t_stamp": "1775934008",
      "s_stamp": "1775941500",
      "url_license": "https://etslive-v3-vidio-com-preview-tokenized.akamaized.net/live/17852/master.m3u8?hdnts=exp=1726126994~acl=/live/17852/master.m3u8!/hls-p/ingest_17852*/*!/hls-b/ingest_17852*/*~id=851110~hmac=7d99eba92a995ff011bebd28413b2ce3115295b25a6ae91d4de3686d5bc3b954",
      "fake_event": "f",
      "header_iptv": "{\"Host\":\"live1.pro2cdnlive.com\",\"Referer\":\"https://xl365.plcdn.xyz/\",\"Origin\":\"https://xl365.plcdn.xyz\",\"User-Agent\":\"Mozilla/5.0 (Windows NT 10.0; Win64; x64; rv:134.0) Gecko/20100101 Firefox/134.0\"}",
      "header_license": "{\"x-data\":\"none\"}",
      "category": "Events"
    },
    {
      "id": "3347",
      "name": "Spanish: LaLiga Retro [CH4]",
      "tagline": "12 Apr 02:00 WIB - Sevilla FC vs Atletico Madrid",
      "hls": "http://otte.live.fly.ww.aiv-cdn.net/syd-nitro/live/clients/dash/enc/8m8cd46i1t/out/v1/83985c68e4174e90a58a1f2c024be4c9/cenc.mpd",
      "namespace": "Spanish: La Liga [CH4]",
      "is_live": "t",
      "is_movie": "f",
      "subtitle": "",
      "image": "https://api.orcatv.my.id/orca-stream/data-v1/source-images/eb9bd930b5e8254504bc1be87c9e75909ab733374667f8f2c92a86fd1c02406f.png",
      "jenis": "dash-clearkey",
      "premium": "f",
      "alpha_2_code": "EV",
      "country_name": "Events",
      "t_stamp": "1775934008",
      "s_stamp": "1775941500",
      "url_license": "eyJrZXlzIjpbeyJrdHkiOiJvY3QiLCJrIjoicmlRSkFTTzR4eXJGUUUzQlVvUjh1QSIsImtpZCI6IkMwSytKbVRYNkJIUVR6NVFUZ2treFEifV0sInR5cGUiOiJ0ZW1wb3JhcnkifQ==",
      "fake_event": "f",
      "header_iptv": "{\"Referer\":\"none\",\"Origin\":\"none\",\"User-Agent\":\"Mozilla/5.0 (Windows NT 10.0; Win64; x64; rv:123.0) Gecko/20100101 Firefox/123.0\"}",
      "header_license": "{\"x-data\":\"none\"}",
      "category": "Events"
    },
    {
      "id": "3873",
      "name": "France: Ligue 1 [CH2]",
      "tagline": "12 Apr 02:05 WIB - Stade Rennais FC vs Angers SCO",
      "hls": "http://140.150.22.205/live/channel2.flv?wsSecret=2febdf8123bd6ddc48c68a041bb6ed9d&wsABSTime=1775410809",
      "namespace": "France: Ligue 1 [CH2]",
      "is_live": "t",
      "is_movie": "f",
      "subtitle": "",
      "image": "https://api.orcatv.my.id/orca-stream/data-v1/source-images/0ad5416060eac8bb6ac7bf7e9ffc8b8d4d168f1b2d092e5fa8317b773edad51e.png",
      "jenis": "ts",
      "premium": "f",
      "alpha_2_code": "EV",
      "country_name": "Events",
      "t_stamp": "1775934308",
      "s_stamp": "1775941800",
      "url_license": "https://etslive-v3-vidio-com-preview-tokenized.akamaized.net/live/17852/master.m3u8?hdnts=exp=1726126994~acl=/live/17852/master.m3u8!/hls-p/ingest_17852*/*!/hls-b/ingest_17852*/*~id=851110~hmac=7d99eba92a995ff011bebd28413b2ce3115295b25a6ae91d4de3686d5bc3b954",
      "fake_event": "f",
      "header_iptv": "{\"Host\":\"live1.pro2cdnlive.com\",\"Referer\":\"https://xl365.plcdn.xyz/\",\"Origin\":\"https://xl365.plcdn.xyz\",\"User-Agent\":\"Mozilla/5.0 (Windows NT 10.0; Win64; x64; rv:134.0) Gecko/20100101 Firefox/134.0\"}",
      "header_license": "{\"x-data\":\"none\"}",
      "category": "Events"
    },
    {
      "id": "2545",
      "name": "UFC 327 [CH1]",
      "tagline": "12 Apr 04:30 WIB - Kaseya Center, Miami, FL",
      "hls": "https://abkv2pxaaaaaaaamms3xu2tu2eynb.ta.bia-cf.live.pv-cdn.net/iad-nitro/live/clients/dash/enc/cllekigzzn/out/v1/bd3b0c314fff4bb1ab4693358f3cd2d3/cenc.mpd",
      "namespace": "UFC Fight Night [CH1]",
      "is_live": "t",
      "is_movie": "f",
      "subtitle": "https://qw.live.pv-cdn.net/OTTB/iad-nitro/live/clients/dash/enc/cllekigzzn/out/v1/bd3b0c314fff4bb1ab4693358f3cd2d3/cenc.mpd",
      "image": "https://api.orcatv.my.id/orca-stream/data-v1/source-images/3ecfc40b240e0dc46e9b995fdd59a7c65e1e94f0d79f53287862570b72a246a3.png",
      "jenis": "dash-clearkey",
      "premium": "f",
      "alpha_2_code": "EV",
      "country_name": "Events",
      "t_stamp": "1775943000",
      "s_stamp": "1775962800",
      "url_license": "eyJrZXlzIjpbeyJrdHkiOiJvY3QiLCJrIjoiVWhTUEVFTFNPSVNmQ25nVDhkcUtldyIsImtpZCI6IktVdFhZYzc4SXRER01TazU0VDJDZUEifV0sInR5cGUiOiJ0ZW1wb3JhcnkifQ==",
      "fake_event": "f",
      "header_iptv": "{\"Referer\":\"none\",\"Origin\":\"none\",\"User-Agent\":\"Mozilla/5.0 (Windows NT 10.0; Win64; x64; rv:120.0) Gecko/20100101 Firefox/120.0\"}",
      "header_license": "{\"x-data\":\"none\",\"old_key\":\"5deb190b1dac28e46c0bdada7668b7de:ddd2b372702e42b0d2708a70b91dec8d\"}",
      "category": "Events"
    },
    {
      "id": "2757",
      "name": "Major League Soccer [CH1]",
      "tagline": "12 Apr 06:30 WIB - Inter Miami vs New York RB",
      "hls": "http://140.150.22.205/live/channel11.flv?wsSecret=e0ed3bf1c0d410d0a8cd8f483b361a86&wsABSTime=1775421422",
      "namespace": "Major League Soccer [CH1]",
      "is_live": "t",
      "is_movie": "f",
      "subtitle": "",
      "image": "https://api.orcatv.my.id/orca-stream/data-v1/source-images/f605938be462a80b66385bf2c49ec76c569e9108ec55155f535e311844f109c3.png",
      "jenis": "ts",
      "premium": "f",
      "alpha_2_code": "EV",
      "country_name": "Events",
      "t_stamp": "1775950200",
      "s_stamp": "1775957400",
      "url_license": "https://etslive-v3-vidio-com-preview-tokenized.akamaized.net/live/17852/master.m3u8?hdnts=exp=1726126994~acl=/live/17852/master.m3u8!/hls-p/ingest_17852*/*!/hls-b/ingest_17852*/*~id=851110~hmac=7d99eba92a995ff011bebd28413b2ce3115295b25a6ae91d4de3686d5bc3b954",
      "fake_event": "f",
      "header_iptv": "{\"Host\":\"live1.pro2cdnlive.com\",\"Referer\":\"https://xl365.plcdn.xyz/\",\"Origin\":\"https://xl365.plcdn.xyz\",\"User-Agent\":\"Mozilla/5.0 (Windows NT 10.0; Win64; x64; rv:134.0) Gecko/20100101 Firefox/134.0\"}",
      "header_license": "{\"x-data\":\"none\"}",
      "category": "Events"
    },
    {
      "id": "813",
      "name": "Indonesia: BRI Super League [CH1]",
      "tagline": "12 Apr 15:30 WIB - Persis Solo FC vs Semen Padang",
      "hls": "http://140.150.22.205/live/channel8.flv?wsSecret=ce4fe514454a92adc84d8a15590d0dfc&wsABSTime=1775910165",
      "namespace": "Indonesia: BRI Super League[CH1]",
      "is_live": "t",
      "is_movie": "f",
      "subtitle": "",
      "image": "https://api.orcatv.my.id/orca-stream/data-v1/source-images/a2588b00b3fe83860cdfe3b7b47bd6926cc08b6448be3ed25f0f18602fc9a7a0.png",
      "jenis": "ts",
      "premium": "f",
      "alpha_2_code": "EV",
      "country_name": "Events",
      "t_stamp": "1775982608",
      "s_stamp": "1775990100",
      "url_license": "https://etslive-v3-vidio-com-preview-tokenized.akamaized.net/live/17852/master.m3u8?hdnts=exp=1726126994~acl=/live/17852/master.m3u8!/hls-p/ingest_17852*/*!/hls-b/ingest_17852*/*~id=851110~hmac=7d99eba92a995ff011bebd28413b2ce3115295b25a6ae91d4de3686d5bc3b954",
      "fake_event": "f",
      "header_iptv": "{\"Host\":\"live1.pro2cdnlive.com\",\"Referer\":\"https://xl365.plcdn.xyz/\",\"Origin\":\"https://xl365.plcdn.xyz\",\"User-Agent\":\"Mozilla/5.0 (Windows NT 10.0; Win64; x64; rv:134.0) Gecko/20100101 Firefox/134.0\"}",
      "header_license": "{\"x-data\":\"none\"}",
      "category": "Events"
    },
    {
      "id": "3957",
      "name": "ASEAN Futsal Championship [CH1]",
      "tagline": "12 Apr 17:00 WIB - Australia vs Vietnam",
      "hls": "https://d2xz2v5wuvgur6.cloudfront.net/out/v1/63c0da12bb4d48afbaf053f51dff2353/index.mpd",
      "namespace": "ASEAN Futsal Championship [CH1]",
      "is_live": "t",
      "is_movie": "f",
      "subtitle": "",
      "image": "https://api.orcatv.my.id/orca-stream/data-v1/source-images/eaff92b91764205a7dfc86ef281a239cb8aac1314c3235273fc95e519a7539ab.png",
      "jenis": "dash-clearkey",
      "premium": "f",
      "alpha_2_code": "EV",
      "country_name": "Events",
      "t_stamp": "1775988000",
      "s_stamp": "1775995200",
      "url_license": "eyJrZXlzIjpbeyJrdHkiOiJvY3QiLCJrIjoiWnpkN2pVS1dBL2kvTU1GaHZhSnA1USIsImtpZCI6IlFEVXlPbi9tUjJlcmp6TkY3WnVUdmcifV0sInR5cGUiOiJ0ZW1wb3JhcnkifQ==",
      "fake_event": "f",
      "header_iptv": "{\"Referer\":\"https://visionplus.id/\",\"Origin\":\"https://visionplus.id\",\"User-Agent\":\"Mozilla/5.0 (Windows NT 10.0; Win64; x64) AppleWebKit/537.36 (KHTML, like Gecko) Chrome/108.0.0.0 Safari/537.36\"}",
      "header_license": "{\"widevine\":\"https://mrpw.ptmnc01.verspective.net/?deviceId=NDIzMDJhZmUtYWRjMi0zNGJkLTkyN2EtYmE1ZDFlZWIwODEz\",\"User-Agent\":\"Mozilla/5.0 (Macintosh; Intel Mac OS X 10_12_6 RTSP-Dogkiller)\"}",
      "category": "Events"
    },
    {
      "id": "3318",
      "name": "Indonesia: BRI Super League [CH3]",
      "tagline": "12 Apr 19:00 WIB - Persib Bandung vs Bali United",
      "hls": "https://cxyznt3-cf.didjhfyu8yg.sbs/auth%3D8bf9cc5a79f4e975b3c251e43e33a8d7e7a98a3f0e84dfff49f32876e3f931cf11858bcaf315e3481da6ecb8622b5da4a40e03b24ffc12aaa35bb60615ad1caafcefe903fc08e8a9857eb50dcd02cb74f5e3044da247f195483dfa0787b6c873249634f4aa2a969af87a3032686938a5613e8715cf2d7e958ac127d3e2b3e3fd5fdbedf26b263c5e89e92d62ce5980f514f40ce24fd6f3e634d59903474a87f8d99892878c57bb25570ca2dcb5a7b456%26cid%3DDutAfpq16Isbzi6yiHRb2260406%26_v%3D2%26_r%3Df9ynjV%26_vis%3Dbd2d08a3bc52137723b4e742a3c8779497fb53fa11d92e7cd1b06022991aa091%26_vvs%3Da1f182077f2255ef076e410f976ed877224503489d9beed38040d2eef60f962c%26_vas%3Df050fc479b7261c3718898ab82289aeedeb4e97826a4b70e5d480fac3539c6ac/app/c416100.m3u8",
      "namespace": "Indonesia: BRI Super League[CH3]",
      "is_live": "t",
      "is_movie": "f",
      "subtitle": "",
      "image": "https://api.orcatv.my.id/orca-stream/data-v1/source-images/a2588b00b3fe83860cdfe3b7b47bd6926cc08b6448be3ed25f0f18602fc9a7a0.png",
      "jenis": "hls",
      "premium": "f",
      "alpha_2_code": "EV",
      "country_name": "Events",
      "t_stamp": "1775995208",
      "s_stamp": "1776002700",
      "url_license": "4b203316c47c370a1eb9097c070d7226:676e6783f23789cdf4ff0486386145ed",
      "fake_event": "f",
      "header_iptv": "{\"Referer\":\"https://ppdd18.plaifrdcikf.shop/\",\"Origin\":\"https://ppdd18.plaifrdcikf.shop\",\"User-Agent\":\"Mozilla/5.0 (Windows NT 10.0; Win64; x64) AppleWebKit/537.36 (KHTML, like Gecko) Chrome/139.0.0.0 Safari/537.36\",\"Sec-Fetch-Site\":\"cross-site\",\"Sec-Fetch-Mode\":\"cors\",\"Sec-Fetch-Dest\":\"empty\",\"Connection\":\"keep-alive\",\"Accept-Language\":\"en-US,en;q=0.9\",\"Accept-Encoding\":\"gzip, deflate, br, zstd\",\"Accept\":\"*/*\"}",
      "header_license": "{\"x-data\":\"none\"}",
      "category": "Events"
    },
    {
      "id": "3326",
      "name": "Indonesia: BRI Super League [CH5]",
      "tagline": "12 Apr 19:00 WIB - Malut United vs Dewa United FC",
      "hls": "http://47.246.20.185/livecdn/channel67.flv?auth_key=3000001775867171-0-0-33b39223e91a5157536cbb85c5836ff4",
      "namespace": "Indonesia: BRI Super League[CH5]",
      "is_live": "t",
      "is_movie": "f",
      "subtitle": "",
      "image": "https://api.orcatv.my.id/orca-stream/data-v1/source-images/a2588b00b3fe83860cdfe3b7b47bd6926cc08b6448be3ed25f0f18602fc9a7a0.png",
      "jenis": "ts",
      "premium": "f",
      "alpha_2_code": "EV",
      "country_name": "Events",
      "t_stamp": "1775995208",
      "s_stamp": "1776002700",
      "url_license": "https://etslive-v3-vidio-com-preview-tokenized.akamaized.net/live/17852/master.m3u8?hdnts=exp=1726126994~acl=/live/17852/master.m3u8!/hls-p/ingest_17852*/*!/hls-b/ingest_17852*/*~id=851110~hmac=7d99eba92a995ff011bebd28413b2ce3115295b25a6ae91d4de3686d5bc3b954",
      "fake_event": "f",
      "header_iptv": "{\"Host\":\"live3.procdnlive.com\",\"Referer\":\"https://xlz.plcdn.xyz/\",\"Origin\":\"https://xlz.plcdn.xyz\",\"User-Agent\":\"Mozilla/5.0 (Windows NT 10.0; Win64; x64; rv:134.0) Gecko/20100101 Firefox/134.0\"}",
      "header_license": "{\"x-data\":\"none\"}",
      "category": "Events"
    },
    {
      "id": "3958",
      "name": "ASEAN Futsal Championship [CH2]",
      "tagline": "12 Apr 20:00 WIB - Thailand vs Indonesia",
      "hls": "https://d2xz2v5wuvgur6.cloudfront.net/out/v1/63c0da12bb4d48afbaf053f51dff2353/index.mpd",
      "namespace": "ASEAN Futsal Championship [CH2]",
      "is_live": "t",
      "is_movie": "f",
      "subtitle": "",
      "image": "https://api.orcatv.my.id/orca-stream/data-v1/source-images/eaff92b91764205a7dfc86ef281a239cb8aac1314c3235273fc95e519a7539ab.png",
      "jenis": "dash-clearkey",
      "premium": "f",
      "alpha_2_code": "EV",
      "country_name": "Events",
      "t_stamp": "1775998800",
      "s_stamp": "1776006000",
      "url_license": "eyJrZXlzIjpbeyJrdHkiOiJvY3QiLCJrIjoiWnpkN2pVS1dBL2kvTU1GaHZhSnA1USIsImtpZCI6IlFEVXlPbi9tUjJlcmp6TkY3WnVUdmcifV0sInR5cGUiOiJ0ZW1wb3JhcnkifQ==",
      "fake_event": "f",
      "header_iptv": "{\"Referer\":\"https://visionplus.id/\",\"Origin\":\"https://visionplus.id\",\"User-Agent\":\"Mozilla/5.0 (Windows NT 10.0; Win64; x64) AppleWebKit/537.36 (KHTML, like Gecko) Chrome/108.0.0.0 Safari/537.36\"}",
      "header_license": "{\"widevine\":\"https://mrpw.ptmnc01.verspective.net/?deviceId=NDIzMDJhZmUtYWRjMi0zNGJkLTkyN2EtYmE1ZDFlZWIwODEz\",\"User-Agent\":\"Mozilla/5.0 (Macintosh; Intel Mac OS X 10_12_6 RTSP-Dogkiller)\"}",
      "category": "Events"
    },
    {
      "id": "3874",
      "name": "France: Ligue 1 [CH3]",
      "tagline": "12 Apr 22:15 WIB - Toulouse FC vs LOSC Lille",
      "hls": "http://140.150.22.205/live/channel13.flv?wsSecret=065ad5a01cd37afa493b3a0254ab7dd4&wsABSTime=1775319843",
      "namespace": "France: Ligue 1 [CH3]",
      "is_live": "t",
      "is_movie": "f",
      "subtitle": "",
      "image": "https://api.orcatv.my.id/orca-stream/data-v1/source-images/0ad5416060eac8bb6ac7bf7e9ffc8b8d4d168f1b2d092e5fa8317b773edad51e.png",
      "jenis": "ts",
      "premium": "f",
      "alpha_2_code": "EV",
      "country_name": "Events",
      "t_stamp": "1776006908",
      "s_stamp": "1776014400",
      "url_license": "https://etslive-v3-vidio-com-preview-tokenized.akamaized.net/live/17852/master.m3u8?hdnts=exp=1726126994~acl=/live/17852/master.m3u8!/hls-p/ingest_17852*/*!/hls-b/ingest_17852*/*~id=851110~hmac=7d99eba92a995ff011bebd28413b2ce3115295b25a6ae91d4de3686d5bc3b954",
      "fake_event": "f",
      "header_iptv": "{\"Host\":\"live1.pro2cdnlive.com\",\"Referer\":\"https://xl365.plcdn.xyz/\",\"Origin\":\"https://xl365.plcdn.xyz\",\"User-Agent\":\"Mozilla/5.0 (Windows NT 10.0; Win64; x64; rv:134.0) Gecko/20100101 Firefox/134.0\"}",
      "header_license": "{\"x-data\":\"none\"}",
      "category": "Events"
    }
  ],
  "countrylist": [
    {
      "country_name": "Events",
      "alpha_2_code": "EV",
      "alpha_3_code": "EVE",
      "numeric_alpha": "1",
      "emoji": null,
      "numeric": "1"
    },
    {
      "country_name": "Movies",
      "alpha_2_code": "MI",
      "alpha_3_code": "MOV",
      "numeric_alpha": "8",
      "emoji": null,
      "numeric": "8"
    },
    {
      "country_name": "Sports TV",
      "alpha_2_code": "SP",
      "alpha_3_code": "SPT",
      "numeric_alpha": "9",
      "emoji": null,
      "numeric": "9"
    },
    {
      "country_name": "Australia",
      "alpha_2_code": "AU",
      "alpha_3_code": "AUS",
      "numeric_alpha": "36",
      "emoji": null,
      "numeric": "36"
    },
    {
      "country_name": "Brazil",
      "alpha_2_code": "BR",
      "alpha_3_code": "BRA",
      "numeric_alpha": "76",
      "emoji": null,
      "numeric": "76"
    },
    {
      "country_name": "Kids",
      "alpha_2_code": "KD",
      "alpha_3_code": "KDS",
      "numeric_alpha": "162",
      "emoji": null,
      "numeric": "162"
    },
    {
      "country_name": "Indonesia",
      "alpha_2_code": "ID",
      "alpha_3_code": "IDN",
      "numeric_alpha": "360",
      "emoji": null,
      "numeric": "360"
    },
    {
      "country_name": "Japan",
      "alpha_2_code": "JP",
      "alpha_3_code": "JPN",
      "numeric_alpha": "392",
      "emoji": null,
      "numeric": "392"
    },
    {
      "country_name": "South Korea",
      "alpha_2_code": "KR",
      "alpha_3_code": "KOR",
      "numeric_alpha": "410",
      "emoji": null,
      "numeric": "410"
    },
    {
      "country_name": "Malaysia",
      "alpha_2_code": "MY",
      "alpha_3_code": "MYS",
      "numeric_alpha": "458",
      "emoji": null,
      "numeric": "458"
    },
    {
      "country_name": "Saudi Arabia",
      "alpha_2_code": "SA",
      "alpha_3_code": "SAU",
      "numeric_alpha": "682",
      "emoji": null,
      "numeric": "682"
    },
    {
      "country_name": "Singapore",
      "alpha_2_code": "SG",
      "alpha_3_code": "SGP",
      "numeric_alpha": "702",
      "emoji": null,
      "numeric": "702"
    },
    {
      "country_name": "United Kingdom",
      "alpha_2_code": "GB",
      "alpha_3_code": "GBR",
      "numeric_alpha": "826",
      "emoji": null,
      "numeric": "826"
    },
    {
      "country_name": "TVRI",
      "alpha_2_code": "RI",
      "alpha_3_code": "TVR",
      "numeric_alpha": "902",
      "emoji": null,
      "numeric": "902"
    },
    {
      "country_name": "TV Lokal",
      "alpha_2_code": "LO",
      "alpha_3_code": "LOK",
      "numeric_alpha": "909",
      "emoji": null,
      "numeric": "909"
    }
  ]
}
